piifinder/__init__.py
piifinder/cli.py
piifinder/scanner.py
piifinder-0.0.3.dist-info/METADATA
piifinder-0.0.3.dist-info/WHEEL
piifinder-0.0.3.dist-info/entry_points.txt
piifinder-0.0.3.dist-info/top_level.txt
piifinder-0.0.3.dist-info/RECORD
